[{"name":"Kennedy Martin","team":"Penn State","sets":76,"assists":11,"kills":434,"digs":176,"blocks":55.0,"aces":35,"points":1922.0,"points per set":25.3},{"name":"Claire Ammeraal","team":"Iowa","sets":83,"assists":798,"kills":108,"digs":198,"blocks":43.0,"aces":6,"points":1797.0,"points per set":21.7},{"name":"Taylor Anderson","team":"Purdue","sets":76,"assists":811,"kills":58,"digs":163,"blocks":49.0,"aces":11,"points":1673.0,"points per set":22.0},{"name":"Kate Duffey","team":"UCLA","sets":72,"assists":741,"kills":24,"digs":170,"blocks":38.0,"aces":16,"points":1573.0,"points per set":21.8},{"name":"Reese Messer","team":"USC","sets":72,"assists":787,"kills":40,"digs":167,"blocks":37.0,"aces":9,"points":1569.0,"points per set":21.8},{"name":"Alanah Clemente","team":"Oregon","sets":76,"assists":15,"kills":318,"digs":108,"blocks":48.0,"aces":43,"points":1549.0,"points per set":20.4},{"name":"Kenna Phelan","team":"Illinois","sets":72,"assists":706,"kills":37,"digs":181,"blocks":30.0,"aces":13,"points":1543.0,"points per set":21.4},{"name":"Stella Swenson","team":"Minnesota","sets":73,"assists":679,"kills":34,"digs":146,"blocks":39.0,"aces":24,"points":1542.0,"points per set":21.1},{"name":"Alexis Haury","team":"Washington","sets":75,"assists":682,"kills":18,"digs":194,"blocks":28.0,"aces":15,"points":1534.0,"points per set":20.5},{"name":"Cora Taylor","team":"Oregon","sets":76,"assists":758,"kills":29,"digs":148,"blocks":26.0,"aces":17,"points":1508.0,"points per set":19.8},{"name":"Addie Lyon","team":"Penn State","sets":76,"assists":805,"kills":17,"digs":124,"blocks":29.0,"aces":18,"points":1478.0,"points per set":19.4},{"name":"Teodora Kri\u010dkovi\u0107","team":"Indiana","sets":70,"assists":734,"kills":36,"digs":125,"blocks":27.0,"aces":21,"points":1472.0,"points per set":21.0},{"name":"Ayah Elnady","team":"Northwestern","sets":82,"assists":21,"kills":266,"digs":187,"blocks":24.0,"aces":27,"points":1456.0,"points per set":17.8},{"name":"Mimi Colyer","team":"Wisconsin","sets":65,"assists":9,"kills":345,"digs":145,"blocks":48.0,"aces":16,"points":1438.0,"points per set":22.1},{"name":"Bergen Reilly","team":"Nebraska","sets":60,"assists":640,"kills":44,"digs":152,"blocks":45.0,"aces":11,"points":1429.0,"points per set":23.8},{"name":"Mia Tuman","team":"Ohio State","sets":75,"assists":640,"kills":34,"digs":167,"blocks":29.0,"aces":13,"points":1426.0,"points per set":19.0},{"name":"Lily Bolen","team":"Rutgers","sets":70,"assists":630,"kills":16,"digs":165,"blocks":18.0,"aces":21,"points":1421.0,"points per set":20.3},{"name":"Lauren Carter","team":"Northwestern","sets":82,"assists":499,"kills":11,"digs":156,"blocks":5.0,"aces":33,"points":1334.0,"points per set":16.3},{"name":"Julia Hanson","team":"Minnesota","sets":72,"assists":4,"kills":286,"digs":120,"blocks":45.0,"aces":26,"points":1331.0,"points per set":18.5},{"name":"Kierstyn Barton","team":"Washington","sets":75,"assists":15,"kills":260,"digs":168,"blocks":32.0,"aces":19,"points":1325.0,"points per set":17.7},{"name":"Allison Jacobs","team":"Michigan","sets":76,"assists":29,"kills":284,"digs":140,"blocks":42.0,"aces":16,"points":1303.0,"points per set":17.1},{"name":"Kenna Wollard","team":"Purdue","sets":76,"assists":10,"kills":328,"digs":140,"blocks":37.0,"aces":10,"points":1297.0,"points per set":17.1},{"name":"Simona Mateska","team":"Washington","sets":75,"assists":18,"kills":241,"digs":177,"blocks":37.0,"aces":15,"points":1292.0,"points per set":17.2},{"name":"Abigail Mullen","team":"USC","sets":71,"assists":9,"kills":183,"digs":131,"blocks":61.0,"aces":32,"points":1271.0,"points per set":17.9},{"name":"London Wijay","team":"USC","sets":72,"assists":18,"kills":275,"digs":164,"blocks":28.0,"aces":12,"points":1264.0,"points per set":17.6},{"name":"Grace Heaney","team":"Purdue","sets":76,"assists":13,"kills":248,"digs":148,"blocks":56.0,"aces":13,"points":1251.0,"points per set":16.5},{"name":"Malayah Long","team":"Michigan State","sets":76,"assists":593,"kills":24,"digs":145,"blocks":11.0,"aces":14,"points":1249.0,"points per set":16.4},{"name":"Karolina Staniszewska","team":"Michigan State","sets":76,"assists":16,"kills":248,"digs":171,"blocks":24.0,"aces":15,"points":1247.0,"points per set":16.4},{"name":"Jaidyn Jager","team":"Indiana","sets":70,"assists":19,"kills":235,"digs":157,"blocks":27.0,"aces":20,"points":1241.0,"points per set":17.7},{"name":"Lola Schumacher","team":"UCLA","sets":77,"assists":77,"kills":6,"digs":346,"blocks":0.0,"aces":9,"points":1217.0,"points per set":15.8},{"name":"Morgan Burke","team":"Michigan","sets":77,"assists":512,"kills":16,"digs":140,"blocks":9.0,"aces":21,"points":1201.0,"points per set":15.6},{"name":"Lilly Wagner","team":"Maryland","sets":70,"assists":474,"kills":28,"digs":145,"blocks":29.0,"aces":13,"points":1182.0,"points per set":16.9},{"name":"Chard'e Vanzandt","team":"Iowa","sets":83,"assists":9,"kills":274,"digs":102,"blocks":27.0,"aces":22,"points":1164.0,"points per set":14.0},{"name":"Alyssa Aguayo","team":"Illinois","sets":72,"assists":27,"kills":199,"digs":167,"blocks":19.0,"aces":17,"points":1153.0,"points per set":16.0},{"name":"Harper Murray","team":"Nebraska","sets":61,"assists":25,"kills":210,"digs":128,"blocks":37.0,"aces":21,"points":1150.0,"points per set":18.9},{"name":"Alexa Markley","team":"Washington","sets":75,"assists":8,"kills":205,"digs":136,"blocks":60.0,"aces":13,"points":1136.0,"points per set":15.1},{"name":"Ajack Malual","team":"Maryland","sets":70,"assists":16,"kills":229,"digs":101,"blocks":56.0,"aces":19,"points":1135.0,"points per set":16.2},{"name":"Candela Alonso-Corcelles","team":"Indiana","sets":70,"assists":18,"kills":234,"digs":134,"blocks":42.0,"aces":12,"points":1134.0,"points per set":16.2},{"name":"Olivia Hasbrook","team":"Ohio State","sets":75,"assists":73,"kills":1,"digs":240,"blocks":0.0,"aces":33,"points":1125.0,"points per set":15.0},{"name":"Gillian Grimes","team":"Penn State","sets":76,"assists":65,"kills":3,"digs":289,"blocks":0.0,"aces":18,"points":1118.0,"points per set":14.7},{"name":"Valentina Vaulet","team":"Oregon","sets":76,"assists":12,"kills":243,"digs":67,"blocks":26.0,"aces":34,"points":1117.0,"points per set":14.7},{"name":"Cheridyn Leverette","team":"UCLA","sets":77,"assists":6,"kills":311,"digs":94,"blocks":26.0,"aces":11,"points":1098.0,"points per set":14.3},{"name":"Ryan McAleer","team":"Purdue","sets":76,"assists":96,"kills":3,"digs":274,"blocks":0.0,"aces":17,"points":1094.0,"points per set":14.4},{"name":"Carly Gilk","team":"Minnesota","sets":71,"assists":19,"kills":160,"digs":138,"blocks":40.0,"aces":22,"points":1093.0,"points per set":15.4},{"name":"Zoria Heard","team":"Washington","sets":75,"assists":59,"kills":2,"digs":291,"blocks":0.0,"aces":14,"points":1076.0,"points per set":14.3},{"name":"Sophia Meyers","team":"Oregon","sets":73,"assists":18,"kills":191,"digs":152,"blocks":31.0,"aces":10,"points":1049.0,"points per set":14.4},{"name":"Una Vajagic","team":"Wisconsin","sets":65,"assists":25,"kills":187,"digs":167,"blocks":19.0,"aces":7,"points":1027.0,"points per set":15.8},{"name":"Rylen Reid","team":"Northwestern","sets":65,"assists":4,"kills":218,"digs":93,"blocks":23.0,"aces":23,"points":1018.0,"points per set":15.7},{"name":"Lia Schneider","team":"Michigan State","sets":76,"assists":74,"kills":2,"digs":245,"blocks":0.0,"aces":20,"points":1013.0,"points per set":13.3},{"name":"Ella Demetrician","team":"Michigan","sets":71,"assists":14,"kills":199,"digs":132,"blocks":30.0,"aces":11,"points":1008.0,"points per set":14.2},{"name":"Maddi Cuchran","team":"Michigan","sets":77,"assists":92,"kills":1,"digs":251,"blocks":0.0,"aces":15,"points":997.0,"points per set":12.9},{"name":"Bianca Mumcular","team":"Michigan State","sets":75,"assists":13,"kills":213,"digs":96,"blocks":39.0,"aces":13,"points":974.0,"points per set":13.0},{"name":"Milana Moisio","team":"Iowa","sets":83,"assists":69,"kills":1,"digs":285,"blocks":0.0,"aces":1,"points":936.0,"points per set":11.3},{"name":"Marianna Singletary","team":"UCLA","sets":77,"assists":5,"kills":185,"digs":41,"blocks":101.0,"aces":13,"points":931.0,"points per set":12.1},{"name":"Lexi Visintine","team":"Rutgers","sets":70,"assists":7,"kills":161,"digs":98,"blocks":19.0,"aces":25,"points":930.0,"points per set":13.3},{"name":"Hannah Jones","team":"Ohio State","sets":68,"assists":10,"kills":222,"digs":84,"blocks":33.0,"aces":12,"points":925.0,"points per set":13.6},{"name":"Taryn Kirsch","team":"Illinois","sets":72,"assists":72,"kills":0,"digs":243,"blocks":0.0,"aces":9,"points":891.0,"points per set":12.4},{"name":"Aspen Maxwell","team":"Rutgers","sets":70,"assists":5,"kills":199,"digs":75,"blocks":51.0,"aces":9,"points":871.0,"points per set":12.4},{"name":"Addy Horner","team":"Wisconsin","sets":48,"assists":373,"kills":18,"digs":78,"blocks":22.0,"aces":16,"points":869.0,"points per set":18.1},{"name":"McKenna Garr","team":"Minnesota","sets":69,"assists":56,"kills":0,"digs":220,"blocks":0.0,"aces":14,"points":856.0,"points per set":12.4},{"name":"Kristen Simon","team":"Wisconsin","sets":65,"assists":65,"kills":0,"digs":225,"blocks":0.0,"aces":11,"points":850.0,"points per set":13.1},{"name":"Alyssa Worden","team":"Iowa","sets":73,"assists":9,"kills":143,"digs":109,"blocks":17.0,"aces":16,"points":833.0,"points per set":11.4},{"name":"Taylor Deckert","team":"USC","sets":69,"assists":61,"kills":2,"digs":238,"blocks":0.0,"aces":5,"points":829.0,"points per set":12.0},{"name":"Reese Sheppard","team":"Oregon","sets":75,"assists":62,"kills":0,"digs":198,"blocks":0.0,"aces":16,"points":816.0,"points per set":10.9},{"name":"Charlie Fuerbringer","team":"Wisconsin","sets":32,"assists":394,"kills":24,"digs":77,"blocks":22.0,"aces":7,"points":809.0,"points per set":25.3},{"name":"Haley Melby","team":"Maryland","sets":68,"assists":8,"kills":125,"digs":106,"blocks":28.0,"aces":13,"points":790.0,"points per set":11.6},{"name":"Kelly Kinney","team":"Minnesota","sets":69,"assists":8,"kills":161,"digs":48,"blocks":35.0,"aces":21,"points":789.0,"points per set":11.4},{"name":"Andi Jackson","team":"Nebraska","sets":59,"assists":2,"kills":174,"digs":31,"blocks":70.0,"aces":13,"points":783.0,"points per set":13.3},{"name":"Iva Sucurovic","team":"Oregon","sets":76,"assists":7,"kills":118,"digs":41,"blocks":68.0,"aces":20,"points":770.0,"points per set":10.1},{"name":"Alleigh Dutton","team":"Rutgers","sets":67,"assists":55,"kills":2,"digs":182,"blocks":0.0,"aces":15,"points":755.0,"points per set":11.3},{"name":"Avry Tatum","team":"Indiana","sets":70,"assists":5,"kills":215,"digs":41,"blocks":32.0,"aces":10,"points":754.0,"points per set":10.8},{"name":"Julia Kane","team":"Purdue","sets":76,"assists":27,"kills":1,"digs":152,"blocks":0.0,"aces":25,"points":735.0,"points per set":9.7},{"name":"Averie Hernandez","team":"Illinois","sets":72,"assists":8,"kills":67,"digs":128,"blocks":9.0,"aces":18,"points":733.0,"points per set":10.2},{"name":"Ally Williams","team":"Maryland","sets":70,"assists":63,"kills":0,"digs":183,"blocks":0.0,"aces":11,"points":722.0,"points per set":10.3},{"name":"Emmi Sellman","team":"Penn State","sets":76,"assists":8,"kills":155,"digs":102,"blocks":26.0,"aces":2,"points":722.0,"points per set":9.5},{"name":"Grace Egan","team":"Wisconsin","sets":44,"assists":14,"kills":92,"digs":99,"blocks":19.0,"aces":16,"points":712.0,"points per set":16.2},{"name":"Drew Wright","team":"Northwestern","sets":82,"assists":62,"kills":1,"digs":165,"blocks":0.0,"aces":15,"points":709.0,"points per set":8.6},{"name":"Serena Nyambio","team":"Michigan","sets":77,"assists":5,"kills":132,"digs":28,"blocks":104.0,"aces":2,"points":685.0,"points per set":8.9},{"name":"Sienna Noordermeer","team":"Northwestern","sets":80,"assists":304,"kills":0,"digs":103,"blocks":0.0,"aces":7,"points":683.0,"points per set":8.5},{"name":"Aleksandra Stojanovic","team":"Iowa","sets":79,"assists":19,"kills":93,"digs":47,"blocks":52.0,"aces":18,"points":682.0,"points per set":8.6},{"name":"Ava Falduto","team":"Penn State","sets":75,"assists":39,"kills":0,"digs":148,"blocks":0.0,"aces":19,"points":673.0,"points per set":9.0},{"name":"Zuzanna Kulig","team":"Michigan State","sets":71,"assists":5,"kills":115,"digs":24,"blocks":74.0,"aces":14,"points":669.0,"points per set":9.4},{"name":"Reese Wuebker","team":"Ohio State","sets":66,"assists":10,"kills":168,"digs":86,"blocks":7.0,"aces":4,"points":665.0,"points per set":10.1},{"name":"Taylor de Boer","team":"Illinois","sets":71,"assists":1,"kills":258,"digs":27,"blocks":20.0,"aces":0,"points":658.0,"points per set":9.3},{"name":"Jaimie Marquardt","team":"Iowa","sets":83,"assists":25,"kills":0,"digs":132,"blocks":0.0,"aces":23,"points":651.0,"points per set":7.8},{"name":"Hannah Whittingstall","team":"Iowa","sets":74,"assists":13,"kills":152,"digs":20,"blocks":74.0,"aces":5,"points":649.0,"points per set":8.8},{"name":"Akasha Anderson","team":"Purdue","sets":75,"assists":3,"kills":217,"digs":33,"blocks":35.0,"aces":0,"points":641.0,"points per set":8.5},{"name":"Maggie Li","team":"UCLA","sets":45,"assists":5,"kills":130,"digs":92,"blocks":16.0,"aces":4,"points":629.0,"points per set":14.0},{"name":"Adonia Faumuina","team":"USC","sets":70,"assists":5,"kills":185,"digs":34,"blocks":42.0,"aces":1,"points":613.0,"points per set":8.8},{"name":"Carmel Vares","team":"Iowa","sets":79,"assists":1,"kills":209,"digs":24,"blocks":39.0,"aces":0,"points":608.0,"points per set":7.7},{"name":"Eva Rohrbach","team":"Maryland","sets":70,"assists":9,"kills":89,"digs":38,"blocks":64.0,"aces":11,"points":603.0,"points per set":8.6},{"name":"Lourdes Myers","team":"Minnesota","sets":73,"assists":1,"kills":118,"digs":34,"blocks":84.0,"aces":1,"points":601.0,"points per set":8.2},{"name":"Ashlyn Philpot","team":"Illinois","sets":72,"assists":3,"kills":148,"digs":33,"blocks":57.0,"aces":3,"points":599.0,"points per set":8.3},{"name":"Kenzie Cogan","team":"Illinois","sets":71,"assists":18,"kills":1,"digs":137,"blocks":0.0,"aces":16,"points":591.0,"points per set":8.3},{"name":"Jenna DeLaMater","team":"Rutgers","sets":70,"assists":17,"kills":2,"digs":106,"blocks":0.0,"aces":25,"points":589.0,"points per set":8.4},{"name":"Jenna Hanes","team":"Michigan","sets":75,"assists":2,"kills":113,"digs":22,"blocks":74.0,"aces":7,"points":586.0,"points per set":7.8},{"name":"Rebekah Allick","team":"Nebraska","sets":56,"assists":9,"kills":144,"digs":17,"blocks":79.0,"aces":0,"points":585.0,"points per set":10.4},{"name":"Laney Choboy","team":"Nebraska","sets":60,"assists":57,"kills":0,"digs":156,"blocks":0.0,"aces":6,"points":585.0,"points per set":9.8},{"name":"Katy Wessels","team":"Washington","sets":73,"assists":3,"kills":83,"digs":21,"blocks":99.0,"aces":5,"points":579.0,"points per set":7.9},{"name":"Isabella Bullington","team":"Northwestern","sets":78,"assists":5,"kills":190,"digs":36,"blocks":22.0,"aces":2,"points":579.0,"points per set":7.4},{"name":"Carter Booth","team":"Wisconsin","sets":65,"assists":2,"kills":143,"digs":18,"blocks":78.0,"aces":0,"points":576.0,"points per set":8.9},{"name":"Olivia Mauch","team":"Nebraska","sets":58,"assists":45,"kills":0,"digs":138,"blocks":0.0,"aces":11,"points":569.0,"points per set":9.8},{"name":"Virginia Adriano","team":"Nebraska","sets":56,"assists":1,"kills":131,"digs":33,"blocks":38.0,"aces":9,"points":566.0,"points per set":10.1},{"name":"Ashley Carr","team":"Ohio State","sets":74,"assists":8,"kills":122,"digs":37,"blocks":53.0,"aces":4,"points":562.0,"points per set":7.6},{"name":"Campbell Paris","team":"Northwestern","sets":80,"assists":1,"kills":161,"digs":34,"blocks":45.0,"aces":0,"points":560.0,"points per set":7.0},{"name":"Eliana Urzua","team":"UCLA","sets":48,"assists":5,"kills":123,"digs":83,"blocks":12.0,"aces":2,"points":556.0,"points per set":11.6},{"name":"Auburn Tomkinson","team":"Illinois","sets":68,"assists":6,"kills":156,"digs":31,"blocks":46.0,"aces":0,"points":549.0,"points per set":8.1},{"name":"Maggie Mendelson","team":"Penn State","sets":69,"assists":14,"kills":158,"digs":18,"blocks":51.0,"aces":0,"points":537.0,"points per set":7.8},{"name":"Mia Stahler","team":"Ohio State","sets":75,"assists":10,"kills":0,"digs":113,"blocks":0.0,"aces":18,"points":529.0,"points per set":7.1},{"name":"Jessica Smith","team":"Indiana","sets":69,"assists":17,"kills":17,"digs":106,"blocks":2.0,"aces":15,"points":525.0,"points per set":7.6},{"name":"Camille Edwards","team":"Michigan","sets":52,"assists":211,"kills":4,"digs":70,"blocks":0.0,"aces":9,"points":519.0,"points per set":10.0},{"name":"Zora Hardison","team":"Rutgers","sets":65,"assists":1,"kills":140,"digs":16,"blocks":52.0,"aces":3,"points":515.0,"points per set":7.9},{"name":"Victoria Gray","team":"Indiana","sets":70,"assists":1,"kills":111,"digs":28,"blocks":64.0,"aces":0,"points":499.0,"points per set":7.1},{"name":"Teraya Sigler","team":"Nebraska","sets":61,"assists":7,"kills":44,"digs":92,"blocks":4.0,"aces":10,"points":483.0,"points per set":7.9},{"name":"Kat Lutz","team":"UCLA","sets":77,"assists":17,"kills":0,"digs":131,"blocks":0.0,"aces":7,"points":480.0,"points per set":6.2},{"name":"Jordan Taylor","team":"Minnesota","sets":73,"assists":2,"kills":96,"digs":9,"blocks":86.0,"aces":0,"points":479.0,"points per set":6.6},{"name":"Avery Freeman","team":"Indiana","sets":66,"assists":18,"kills":1,"digs":96,"blocks":0.0,"aces":17,"points":478.0,"points per set":7.2},{"name":"Brooklyn Briscoe","team":"UCLA","sets":77,"assists":4,"kills":110,"digs":28,"blocks":56.0,"aces":0,"points":476.0,"points per set":6.2},{"name":"Lauren Dignan","team":"Northwestern","sets":76,"assists":26,"kills":0,"digs":140,"blocks":0.0,"aces":3,"points":476.0,"points per set":6.3},{"name":"Dior Charles","team":"Purdue","sets":72,"assists":1,"kills":83,"digs":20,"blocks":82.0,"aces":0,"points":473.0,"points per set":6.6},{"name":"Kaia Castle","team":"Ohio State","sets":71,"assists":2,"kills":137,"digs":8,"blocks":54.0,"aces":0,"points":462.0,"points per set":6.5},{"name":"Leah Ford","team":"USC","sets":52,"assists":2,"kills":80,"digs":14,"blocks":70.0,"aces":4,"points":454.0,"points per set":8.7},{"name":"Jordan Hopp","team":"Penn State","sets":60,"assists":10,"kills":58,"digs":22,"blocks":57.0,"aces":9,"points":453.0,"points per set":7.6},{"name":"Gala Trubint","team":"USC","sets":72,"assists":23,"kills":1,"digs":129,"blocks":0.0,"aces":4,"points":452.0,"points per set":6.3},{"name":"Alicia Andrew","team":"Wisconsin","sets":65,"assists":8,"kills":90,"digs":13,"blocks":74.0,"aces":0,"points":449.0,"points per set":6.9},{"name":"Gigi Navarrete","team":"Northwestern","sets":76,"assists":22,"kills":0,"digs":107,"blocks":0.0,"aces":10,"points":443.0,"points per set":5.8},{"name":"Tara Garvey","team":"Rutgers","sets":70,"assists":2,"kills":151,"digs":29,"blocks":14.0,"aces":0,"points":433.0,"points per set":6.2},{"name":"Rylie McGinest","team":"USC","sets":52,"assists":3,"kills":98,"digs":12,"blocks":48.0,"aces":5,"points":429.0,"points per set":8.2},{"name":"Kate Thibault","team":"Minnesota","sets":73,"assists":25,"kills":1,"digs":128,"blocks":0.0,"aces":1,"points":421.0,"points per set":5.8},{"name":"Mia Tvrdy","team":"USC","sets":49,"assists":2,"kills":115,"digs":8,"blocks":51.0,"aces":0,"points":409.0,"points per set":8.3},{"name":"Cam Berger","team":"Michigan State","sets":49,"assists":151,"kills":3,"digs":50,"blocks":0.0,"aces":9,"points":397.0,"points per set":8.1},{"name":"Evie Doezema","team":"Michigan State","sets":70,"assists":1,"kills":122,"digs":25,"blocks":25.0,"aces":0,"points":395.0,"points per set":5.6},{"name":"Lydia Johnson","team":"Michigan","sets":59,"assists":5,"kills":88,"digs":27,"blocks":37.0,"aces":2,"points":393.0,"points per set":6.7},{"name":"Taylor Landfair","team":"Nebraska","sets":52,"assists":0,"kills":108,"digs":19,"blocks":26.0,"aces":4,"points":391.0,"points per set":7.5},{"name":"Navea Gauthier","team":"Ohio State","sets":51,"assists":0,"kills":113,"digs":34,"blocks":14.0,"aces":2,"points":390.0,"points per set":7.6},{"name":"Sydney Bryant","team":"Maryland","sets":55,"assists":3,"kills":115,"digs":35,"blocks":14.0,"aces":0,"points":380.0,"points per set":6.9},{"name":"Mina Gunes","team":"Ohio State","sets":26,"assists":4,"kills":37,"digs":48,"blocks":15.0,"aces":11,"points":377.0,"points per set":14.5},{"name":"Jocelyn Nathan","team":"Penn State","sets":70,"assists":10,"kills":2,"digs":108,"blocks":0.0,"aces":2,"points":358.0,"points per set":5.1},{"name":"Natalie Fukumoto","team":"Oregon","sets":75,"assists":16,"kills":1,"digs":113,"blocks":0.0,"aces":0,"points":357.0,"points per set":4.8},{"name":"Natalie Robinson","team":"Rutgers","sets":54,"assists":2,"kills":106,"digs":5,"blocks":42.0,"aces":0,"points":355.0,"points per set":6.6},{"name":"Holley McFadden","team":"Oregon","sets":75,"assists":5,"kills":66,"digs":3,"blocks":68.0,"aces":0,"points":350.0,"points per set":4.7},{"name":"Duru G\u00f6k\u00e7en","team":"Maryland","sets":70,"assists":2,"kills":49,"digs":13,"blocks":70.0,"aces":0,"points":349.0,"points per set":5.0},{"name":"Kayla Burbage","team":"Illinois","sets":52,"assists":3,"kills":55,"digs":20,"blocks":51.0,"aces":2,"points":346.0,"points per set":6.7},{"name":"Cymarah Gordon","team":"Michigan","sets":56,"assists":0,"kills":90,"digs":17,"blocks":36.0,"aces":0,"points":339.0,"points per set":6.1},{"name":"Madison Quest","team":"Wisconsin","sets":40,"assists":4,"kills":56,"digs":31,"blocks":19.0,"aces":7,"points":336.0,"points per set":8.4},{"name":"Bella Simkus","team":"Northwestern","sets":76,"assists":4,"kills":46,"digs":23,"blocks":54.0,"aces":0,"points":327.0,"points per set":4.3},{"name":"Taylah Holdem","team":"Michigan State","sets":33,"assists":2,"kills":59,"digs":42,"blocks":8.0,"aces":5,"points":320.0,"points per set":9.7},{"name":"Carmen Waye","team":"Michigan State","sets":58,"assists":0,"kills":91,"digs":2,"blocks":39.0,"aces":0,"points":305.0,"points per set":5.3},{"name":"Caroline Jurevicius","team":"Penn State","sets":52,"assists":0,"kills":104,"digs":8,"blocks":21.0,"aces":1,"points":305.0,"points per set":5.9},{"name":"Audrey Jackson","team":"Indiana","sets":70,"assists":36,"kills":2,"digs":88,"blocks":0.0,"aces":0,"points":304.0,"points per set":4.3},{"name":"Dani Thomas-Nathan","team":"USC","sets":47,"assists":7,"kills":5,"digs":54,"blocks":0.0,"aces":12,"points":299.0,"points per set":6.4},{"name":"Elise Hani","team":"Washington","sets":47,"assists":2,"kills":62,"digs":7,"blocks":48.0,"aces":0,"points":291.0,"points per set":6.2},{"name":"Julia Hunt","team":"Washington","sets":31,"assists":1,"kills":36,"digs":9,"blocks":30.0,"aces":9,"points":280.0,"points per set":9.0},{"name":"Anastasija Ivkovic","team":"UCLA","sets":39,"assists":3,"kills":62,"digs":16,"blocks":33.0,"aces":0,"points":274.0,"points per set":7.0},{"name":"Hannah Leftridge","team":"Indiana","sets":52,"assists":8,"kills":0,"digs":42,"blocks":0.0,"aces":14,"points":274.0,"points per set":5.3},{"name":"Bianka Lulic","team":"Purdue","sets":48,"assists":3,"kills":51,"digs":11,"blocks":45.0,"aces":0,"points":273.0,"points per set":5.7},{"name":"Kayla Kauffman","team":"Northwestern","sets":60,"assists":0,"kills":31,"digs":9,"blocks":61.0,"aces":0,"points":272.0,"points per set":4.5},{"name":"Gabrielle Nichols","team":"Penn State","sets":50,"assists":1,"kills":58,"digs":9,"blocks":38.0,"aces":1,"points":268.0,"points per set":5.4},{"name":"Ky Clayton","team":"Michigan State","sets":47,"assists":4,"kills":1,"digs":45,"blocks":0.0,"aces":12,"points":261.0,"points per set":5.6},{"name":"Jonna Spohn","team":"Maryland","sets":50,"assists":9,"kills":0,"digs":47,"blocks":0.0,"aces":10,"points":250.0,"points per set":5.0},{"name":"Sakura Codling","team":"UCLA","sets":72,"assists":12,"kills":0,"digs":79,"blocks":0.0,"aces":0,"points":249.0,"points per set":3.5},{"name":"Buse Hazan","team":"Northwestern","sets":19,"assists":2,"kills":57,"digs":25,"blocks":10.0,"aces":2,"points":241.0,"points per set":12.7},{"name":"Madi Sell","team":"Indiana","sets":48,"assists":2,"kills":49,"digs":4,"blocks":38.0,"aces":1,"points":236.0,"points per set":4.9},{"name":"Georgia Lee","team":"Minnesota","sets":73,"assists":13,"kills":0,"digs":24,"blocks":0.0,"aces":15,"points":235.0,"points per set":3.2},{"name":"Lindsey Miller","team":"Purdue","sets":37,"assists":1,"kills":47,"digs":10,"blocks":35.0,"aces":0,"points":230.0,"points per set":6.2},{"name":"Addie Canady","team":"Maryland","sets":48,"assists":8,"kills":0,"digs":56,"blocks":0.0,"aces":5,"points":226.0,"points per set":4.7},{"name":"Greta Schlichter","team":"Iowa","sets":54,"assists":8,"kills":2,"digs":67,"blocks":0.0,"aces":1,"points":223.0,"points per set":4.1},{"name":"Aly Borellis","team":"Rutgers","sets":35,"assists":46,"kills":1,"digs":48,"blocks":1.0,"aces":2,"points":215.0,"points per set":6.1},{"name":"Sienna Foster","team":"Purdue","sets":64,"assists":3,"kills":1,"digs":21,"blocks":0.0,"aces":14,"points":208.0,"points per set":3.2},{"name":"Natalie Wardlow","team":"Wisconsin","sets":64,"assists":1,"kills":1,"digs":21,"blocks":0.0,"aces":14,"points":206.0,"points per set":3.2},{"name":"Sophi Randall","team":"Illinois","sets":55,"assists":33,"kills":0,"digs":32,"blocks":0.0,"aces":7,"points":199.0,"points per set":3.6},{"name":"Taylor Simpson","team":"Washington","sets":28,"assists":83,"kills":0,"digs":29,"blocks":2.0,"aces":2,"points":196.0,"points per set":7.0},{"name":"Carly Hendrickson","team":"UCLA","sets":61,"assists":0,"kills":6,"digs":18,"blocks":3.0,"aces":12,"points":195.0,"points per set":3.2},{"name":"Imani Howell","team":"Rutgers","sets":28,"assists":2,"kills":47,"digs":6,"blocks":22.0,"aces":1,"points":190.0,"points per set":6.8},{"name":"Mya Bolton","team":"Michigan State","sets":45,"assists":4,"kills":0,"digs":29,"blocks":0.0,"aces":9,"points":181.0,"points per set":4.0},{"name":"Megan Verbiest","team":"USC","sets":60,"assists":3,"kills":0,"digs":26,"blocks":0.0,"aces":10,"points":181.0,"points per set":3.0},{"name":"Olivia Ruy","team":"Maryland","sets":30,"assists":2,"kills":46,"digs":18,"blocks":4.0,"aces":2,"points":180.0,"points per set":6.0},{"name":"Phekran PK Kong","team":"UCLA","sets":31,"assists":2,"kills":37,"digs":13,"blocks":21.0,"aces":0,"points":178.0,"points per set":5.7},{"name":"Allison Berent","team":"Iowa","sets":50,"assists":10,"kills":0,"digs":46,"blocks":0.0,"aces":2,"points":168.0,"points per set":3.4},{"name":"Zayna Meyer","team":"UCLA","sets":17,"assists":67,"kills":5,"digs":26,"blocks":4.0,"aces":0,"points":167.0,"points per set":9.8},{"name":"Hallie Steponaitis","team":"Iowa","sets":28,"assists":3,"kills":52,"digs":11,"blocks":8.0,"aces":0,"points":164.0,"points per set":5.9},{"name":"Ella Boersema","team":"Indiana","sets":19,"assists":1,"kills":35,"digs":4,"blocks":22.0,"aces":1,"points":159.0,"points per set":8.4},{"name":"Alexis Ewing","team":"Penn State","sets":32,"assists":0,"kills":46,"digs":8,"blocks":11.0,"aces":0,"points":149.0,"points per set":4.7},{"name":"Kaitlyn Hoffman","team":"Ohio State","sets":37,"assists":2,"kills":0,"digs":31,"blocks":0.0,"aces":5,"points":145.0,"points per set":3.9},{"name":"Alex Acevedo","team":"Minnesota","sets":11,"assists":0,"kills":25,"digs":13,"blocks":2.0,"aces":5,"points":145.0,"points per set":13.2},{"name":"Aniya Warren","team":"Wisconsin","sets":37,"assists":6,"kills":1,"digs":44,"blocks":0.0,"aces":0,"points":140.0,"points per set":3.8},{"name":"Kamiah Gibson","team":"Ohio State","sets":28,"assists":53,"kills":4,"digs":16,"blocks":6.0,"aces":1,"points":137.0,"points per set":4.9},{"name":"Danyle Courtley","team":"Michigan State","sets":14,"assists":0,"kills":17,"digs":23,"blocks":4.0,"aces":1,"points":125.0,"points per set":8.9},{"name":"Abby Yoder","team":"Ohio State","sets":54,"assists":2,"kills":0,"digs":11,"blocks":0.0,"aces":9,"points":125.0,"points per set":2.3},{"name":"Amalia Simmons","team":"Michigan","sets":12,"assists":2,"kills":25,"digs":17,"blocks":3.0,"aces":1,"points":122.0,"points per set":10.2},{"name":"Gabby Dean","team":"Illinois","sets":31,"assists":0,"kills":30,"digs":5,"blocks":15.0,"aces":0,"points":120.0,"points per set":3.9},{"name":"Manaia Ogbechie","team":"Nebraska","sets":13,"assists":0,"kills":28,"digs":2,"blocks":18.0,"aces":0,"points":116.0,"points per set":8.9},{"name":"Rachel Williams","team":"Purdue","sets":54,"assists":2,"kills":0,"digs":17,"blocks":0.0,"aces":6,"points":113.0,"points per set":2.1},{"name":"Annika Sokol","team":"Maryland","sets":17,"assists":59,"kills":0,"digs":18,"blocks":0.0,"aces":0,"points":113.0,"points per set":6.6},{"name":"Campbell Flynn","team":"Nebraska","sets":17,"assists":48,"kills":2,"digs":13,"blocks":0.0,"aces":2,"points":111.0,"points per set":6.5},{"name":"Maija Howse","team":"Washington","sets":23,"assists":1,"kills":26,"digs":7,"blocks":12.0,"aces":0,"points":110.0,"points per set":4.8},{"name":"Sydney Wyman","team":"Ohio State","sets":30,"assists":0,"kills":31,"digs":3,"blocks":13.0,"aces":0,"points":110.0,"points per set":3.7},{"name":"Sydney Schnichels","team":"Michigan","sets":27,"assists":3,"kills":20,"digs":10,"blocks":12.0,"aces":0,"points":109.0,"points per set":4.0},{"name":"Gabrielle Gerry","team":"Northwestern","sets":36,"assists":2,"kills":22,"digs":6,"blocks":14.0,"aces":0,"points":106.0,"points per set":2.9},{"name":"Katie Scherer","team":"Maryland","sets":16,"assists":0,"kills":28,"digs":9,"blocks":7.0,"aces":0,"points":104.0,"points per set":6.5},{"name":"Vivian Campbell","team":"Illinois","sets":40,"assists":2,"kills":0,"digs":14,"blocks":0.0,"aces":5,"points":94.0,"points per set":2.4},{"name":"Allie Sczech","team":"Nebraska","sets":16,"assists":1,"kills":22,"digs":5,"blocks":10.0,"aces":0,"points":90.0,"points per set":5.6},{"name":"Trixie McMillin","team":"Michigan","sets":47,"assists":3,"kills":0,"digs":22,"blocks":0.0,"aces":2,"points":89.0,"points per set":1.9},{"name":"Breccan Scheck","team":"Michigan State","sets":23,"assists":0,"kills":16,"digs":7,"blocks":11.0,"aces":0,"points":86.0,"points per set":3.7},{"name":"Maria Tabacuks","team":"Oregon","sets":18,"assists":3,"kills":19,"digs":5,"blocks":5.0,"aces":1,"points":81.0,"points per set":4.5},{"name":"Ellie White","team":"Michigan","sets":5,"assists":18,"kills":0,"digs":11,"blocks":0.0,"aces":3,"points":81.0,"points per set":16.2},{"name":"Lauren Wilcock","team":"Rutgers","sets":37,"assists":3,"kills":1,"digs":11,"blocks":0.0,"aces":4,"points":78.0,"points per set":2.1},{"name":"Gia McGrew","team":"Iowa","sets":14,"assists":0,"kills":17,"digs":3,"blocks":10.0,"aces":0,"points":73.0,"points per set":5.2},{"name":"Lily Wagner","team":"Northwestern","sets":13,"assists":1,"kills":1,"digs":12,"blocks":0.0,"aces":3,"points":69.0,"points per set":5.3},{"name":"Lauren Crowl","team":"Minnesota","sets":67,"assists":0,"kills":9,"digs":8,"blocks":8.0,"aces":0,"points":66.0,"points per set":1.0},{"name":"Skyler Pierce","team":"Nebraska","sets":11,"assists":0,"kills":15,"digs":6,"blocks":2.0,"aces":1,"points":64.0,"points per set":5.8},{"name":"Ksenija Tomic","team":"Oregon","sets":23,"assists":1,"kills":8,"digs":7,"blocks":1.0,"aces":2,"points":61.0,"points per set":2.7},{"name":"Ava Jo Berry","team":"Washington","sets":34,"assists":1,"kills":0,"digs":9,"blocks":0.0,"aces":3,"points":58.0,"points per set":1.7},{"name":"Lexi Gin","team":"Penn State","sets":49,"assists":1,"kills":0,"digs":12,"blocks":0.0,"aces":2,"points":57.0,"points per set":1.2},{"name":"Brooklyn Tealer","team":"USC","sets":14,"assists":1,"kills":23,"digs":0,"blocks":3.0,"aces":0,"points":56.0,"points per set":4.0},{"name":"Maisie Boesiger","team":"Nebraska","sets":14,"assists":5,"kills":0,"digs":17,"blocks":0.0,"aces":0,"points":56.0,"points per set":4.0},{"name":"Mia Hood","team":"Michigan State","sets":12,"assists":1,"kills":7,"digs":4,"blocks":9.0,"aces":0,"points":54.0,"points per set":4.5},{"name":"Kaila Kalama-Bajet","team":"Rutgers","sets":20,"assists":2,"kills":0,"digs":14,"blocks":0.0,"aces":1,"points":54.0,"points per set":2.7},{"name":"Kamden Mitchell","team":"Oregon","sets":14,"assists":28,"kills":0,"digs":7,"blocks":0.0,"aces":0,"points":49.0,"points per set":3.5},{"name":"Caroline Formankova","team":"Michigan State","sets":16,"assists":1,"kills":8,"digs":3,"blocks":7.0,"aces":0,"points":47.0,"points per set":2.9},{"name":"Makena Rumple","team":"Iowa","sets":10,"assists":0,"kills":12,"digs":2,"blocks":4.0,"aces":0,"points":42.0,"points per set":4.2},{"name":"Maya De Los Reyes","team":"Oregon","sets":17,"assists":0,"kills":0,"digs":4,"blocks":0.0,"aces":3,"points":42.0,"points per set":2.5},{"name":"Karis Willow","team":"Penn State","sets":14,"assists":0,"kills":3,"digs":3,"blocks":5.0,"aces":1,"points":40.0,"points per set":2.9},{"name":"Kathryn Randorf","team":"Northwestern","sets":19,"assists":0,"kills":4,"digs":10,"blocks":0.0,"aces":0,"points":38.0,"points per set":2.0},{"name":"Nataly Moravec","team":"Purdue","sets":13,"assists":1,"kills":12,"digs":4,"blocks":0.0,"aces":0,"points":37.0,"points per set":2.8},{"name":"Charlotte Vinson","team":"Indiana","sets":20,"assists":0,"kills":0,"digs":2,"blocks":0.0,"aces":3,"points":36.0,"points per set":1.8},{"name":"Ava Vickers","team":"Indiana","sets":7,"assists":1,"kills":5,"digs":1,"blocks":7.0,"aces":0,"points":35.0,"points per set":5.0},{"name":"Sade Ilawole","team":"Indiana","sets":7,"assists":10,"kills":0,"digs":8,"blocks":0.0,"aces":0,"points":34.0,"points per set":4.9},{"name":"Mira McCool","team":"Rutgers","sets":12,"assists":0,"kills":5,"digs":3,"blocks":4.0,"aces":0,"points":31.0,"points per set":2.6},{"name":"Allie Hazelwood","team":"USC","sets":7,"assists":14,"kills":1,"digs":3,"blocks":1.0,"aces":0,"points":28.0,"points per set":4.0},{"name":"Carly Greskovics","team":"Michigan","sets":9,"assists":0,"kills":0,"digs":6,"blocks":0.0,"aces":1,"points":28.0,"points per set":3.1},{"name":"Trinity Shadd-Ceres","team":"Wisconsin","sets":6,"assists":3,"kills":4,"digs":4,"blocks":1.0,"aces":0,"points":26.0,"points per set":4.3},{"name":"Jenna Meitzler","team":"Iowa","sets":13,"assists":3,"kills":0,"digs":4,"blocks":0.0,"aces":1,"points":25.0,"points per set":1.9},{"name":"Sarah Vellucci","team":"Michigan State","sets":7,"assists":1,"kills":0,"digs":7,"blocks":0.0,"aces":0,"points":22.0,"points per set":3.1},{"name":"Avery Jesewitz","team":"Rutgers","sets":14,"assists":0,"kills":4,"digs":1,"blocks":0.0,"aces":1,"points":21.0,"points per set":1.5},{"name":"Alex McGillivray","team":"Maryland","sets":18,"assists":2,"kills":0,"digs":6,"blocks":0.0,"aces":0,"points":20.0,"points per set":1.1},{"name":"Marlee Arrington","team":"Oregon","sets":16,"assists":0,"kills":2,"digs":0,"blocks":5.0,"aces":0,"points":19.0,"points per set":1.2},{"name":"Peyton Young","team":"Iowa","sets":5,"assists":0,"kills":3,"digs":1,"blocks":3.0,"aces":0,"points":18.0,"points per set":3.6},{"name":"Orian Drore","team":"Oregon","sets":8,"assists":0,"kills":1,"digs":5,"blocks":0.0,"aces":0,"points":17.0,"points per set":2.1},{"name":"Allie Shondell","team":"Purdue","sets":4,"assists":1,"kills":0,"digs":2,"blocks":0.0,"aces":1,"points":17.0,"points per set":4.2},{"name":"Kiki Horne","team":"UCLA","sets":5,"assists":0,"kills":2,"digs":3,"blocks":1.0,"aces":0,"points":16.0,"points per set":3.2},{"name":"Emma Segal","team":"Indiana","sets":12,"assists":2,"kills":0,"digs":1,"blocks":0.0,"aces":1,"points":15.0,"points per set":1.2},{"name":"Ava Wysocki","team":"Illinois","sets":11,"assists":0,"kills":1,"digs":2,"blocks":2.0,"aces":0,"points":14.0,"points per set":1.3},{"name":"Jacyn Bamis","team":"Michigan","sets":3,"assists":0,"kills":5,"digs":0,"blocks":1.0,"aces":0,"points":13.0,"points per set":4.3},{"name":"Bianca May","team":"Illinois","sets":5,"assists":0,"kills":0,"digs":1,"blocks":0.0,"aces":1,"points":13.0,"points per set":2.6},{"name":"Maile Chan","team":"Wisconsin","sets":11,"assists":0,"kills":0,"digs":3,"blocks":0.0,"aces":0,"points":9.0,"points per set":0.8},{"name":"Nikki Tawil","team":"Maryland","sets":2,"assists":5,"kills":0,"digs":1,"blocks":0.0,"aces":0,"points":8.0,"points per set":4.0},{"name":"Sydney Breon","team":"UCLA","sets":8,"assists":1,"kills":0,"digs":2,"blocks":0.0,"aces":0,"points":7.0,"points per set":0.9},{"name":"Emily Lavin","team":"Iowa","sets":13,"assists":0,"kills":0,"digs":2,"blocks":0.0,"aces":0,"points":6.0,"points per set":0.5},{"name":"Tosia Serafinowska","team":"Wisconsin","sets":3,"assists":0,"kills":1,"digs":0,"blocks":1.0,"aces":0,"points":5.0,"points per set":1.7},{"name":"Avery Daum","team":"Indiana","sets":6,"assists":0,"kills":1,"digs":0,"blocks":1.0,"aces":0,"points":5.0,"points per set":0.8},{"name":"Jillian McCarty","team":"Oregon","sets":2,"assists":0,"kills":1,"digs":1,"blocks":0.0,"aces":0,"points":5.0,"points per set":2.5},{"name":"Catherine Burke","team":"Penn State","sets":1,"assists":0,"kills":0,"digs":0,"blocks":1.0,"aces":0,"points":3.0,"points per set":3.0},{"name":"Marichka Hoshylyk","team":"Iowa","sets":3,"assists":0,"kills":0,"digs":1,"blocks":0.0,"aces":0,"points":3.0,"points per set":1.0},{"name":"Ava Jurevicius","team":"Penn State","sets":3,"assists":0,"kills":0,"digs":1,"blocks":0.0,"aces":0,"points":3.0,"points per set":1.0},{"name":"Olivia Swenson","team":"Minnesota","sets":3,"assists":0,"kills":0,"digs":1,"blocks":0.0,"aces":0,"points":3.0,"points per set":1.0},{"name":"Cari Bohm","team":"Illinois","sets":1,"assists":0,"kills":1,"digs":0,"blocks":0.0,"aces":0,"points":2.0,"points per set":2.0},{"name":"Jada Cerniglia","team":"Wisconsin","sets":2,"assists":1,"kills":0,"digs":0,"blocks":0.0,"aces":0,"points":1.0,"points per set":0.5},{"name":"Morgan Van Wie","team":"Wisconsin","sets":1,"assists":0,"kills":0,"digs":0,"blocks":0.0,"aces":0,"points":0.0,"points per set":0.0},{"name":"Lara Zigic","team":"Illinois","sets":1,"assists":0,"kills":0,"digs":0,"blocks":0.0,"aces":0,"points":0.0,"points per set":0.0},{"name":"Kate Lally","team":"Penn State","sets":2,"assists":0,"kills":0,"digs":0,"blocks":0.0,"aces":0,"points":0.0,"points per set":0.0},{"name":"Addy Benefield","team":"Washington","sets":2,"assists":0,"kills":0,"digs":0,"blocks":0.0,"aces":0,"points":0.0,"points per set":0.0},{"name":"Luca Fickell","team":"Indiana","sets":1,"assists":0,"kills":0,"digs":0,"blocks":0.0,"aces":0,"points":0.0,"points per set":0.0},{"name":"Magdalena Juric","team":"Ohio State","sets":2,"assists":0,"kills":0,"digs":0,"blocks":0.0,"aces":0,"points":0.0,"points per set":0.0},{"name":"Chloe Ng","team":"Minnesota","sets":1,"assists":0,"kills":0,"digs":0,"blocks":0.0,"aces":0,"points":0.0,"points per set":0.0}]